[
  {
    "referrer": "Google",
    "count": 324,
    "uniques": 119
  },
  {
    "referrer": "github.com",
    "count": 88,
    "uniques": 33
  },
  {
    "referrer": "yandex.ru",
    "count": 27,
    "uniques": 15
  },
  {
    "referrer": "automated-testing.info",
    "count": 12,
    "uniques": 7
  },
  {
    "referrer": "testerhome.com",
    "count": 11,
    "uniques": 1
  },
  {
    "referrer": "selene-docs-test.readthedocs.io",
    "count": 10,
    "uniques": 4
  },
  {
    "referrer": "Bing",
    "count": 8,
    "uniques": 1
  },
  {
    "referrer": "Yahoo",
    "count": 7,
    "uniques": 1
  },
  {
    "referrer": "pypi.org",
    "count": 6,
    "uniques": 6
  },
  {
    "referrer": "autotest.how",
    "count": 4,
    "uniques": 2
  }
]