[
  {
    "referrer": "Google",
    "count": 527,
    "uniques": 109
  },
  {
    "referrer": "school.qa.guru",
    "count": 229,
    "uniques": 16
  },
  {
    "referrer": "github.com",
    "count": 167,
    "uniques": 31
  },
  {
    "referrer": "pypi.org",
    "count": 71,
    "uniques": 4
  },
  {
    "referrer": "yashaka.github.io",
    "count": 50,
    "uniques": 3
  },
  {
    "referrer": "yandex.ru",
    "count": 33,
    "uniques": 13
  },
  {
    "referrer": "automated-testing.info",
    "count": 18,
    "uniques": 5
  },
  {
    "referrer": "ya.ru",
    "count": 18,
    "uniques": 4
  },
  {
    "referrer": "qaguruschool.getcourse.ru",
    "count": 18,
    "uniques": 2
  },
  {
    "referrer": "DuckDuckGo",
    "count": 17,
    "uniques": 15
  }
]