[
  {
    "referrer": "Google",
    "count": 361,
    "uniques": 141
  },
  {
    "referrer": "github.com",
    "count": 326,
    "uniques": 37
  },
  {
    "referrer": "qa.guru",
    "count": 221,
    "uniques": 7
  },
  {
    "referrer": "confluence.inno.tech",
    "count": 50,
    "uniques": 2
  },
  {
    "referrer": "ecosia.org",
    "count": 30,
    "uniques": 22
  },
  {
    "referrer": "yandex.ru",
    "count": 18,
    "uniques": 16
  },
  {
    "referrer": "yashaka.github.io",
    "count": 14,
    "uniques": 4
  },
  {
    "referrer": "qwiki.nixs.com",
    "count": 14,
    "uniques": 1
  },
  {
    "referrer": "big3.bitrix24.ru",
    "count": 13,
    "uniques": 1
  },
  {
    "referrer": "automated-testing.info",
    "count": 9,
    "uniques": 3
  }
]