{
  "count": 524,
  "uniques": 59,
  "clones": [
    {
      "timestamp": "2023-05-05T00:00:00Z",
      "count": 167,
      "uniques": 7
    },
    {
      "timestamp": "2023-05-06T00:00:00Z",
      "count": 75,
      "uniques": 8
    },
    {
      "timestamp": "2023-05-07T00:00:00Z",
      "count": 73,
      "uniques": 7
    },
    {
      "timestamp": "2023-05-08T00:00:00Z",
      "count": 40,
      "uniques": 12
    },
    {
      "timestamp": "2023-05-09T00:00:00Z",
      "count": 62,
      "uniques": 7
    },
    {
      "timestamp": "2023-05-10T00:00:00Z",
      "count": 77,
      "uniques": 10
    },
    {
      "timestamp": "2023-05-11T00:00:00Z",
      "count": 30,
      "uniques": 8
    }
  ]
}