[
  {
    "referrer": "Google",
    "count": 177,
    "uniques": 106
  },
  {
    "referrer": "github.com",
    "count": 86,
    "uniques": 37
  },
  {
    "referrer": "ecosia.org",
    "count": 18,
    "uniques": 14
  },
  {
    "referrer": "yandex.ru",
    "count": 13,
    "uniques": 7
  },
  {
    "referrer": "DuckDuckGo",
    "count": 12,
    "uniques": 3
  },
  {
    "referrer": "pypi.org",
    "count": 10,
    "uniques": 6
  },
  {
    "referrer": "qiita.com",
    "count": 8,
    "uniques": 7
  },
  {
    "referrer": "automated-testing.info",
    "count": 6,
    "uniques": 5
  },
  {
    "referrer": "testerhome.com",
    "count": 4,
    "uniques": 3
  },
  {
    "referrer": "secureurl.ukr.net",
    "count": 3,
    "uniques": 2
  }
]