[
  {
    "referrer": "github.com",
    "count": 184,
    "uniques": 25
  },
  {
    "referrer": "Google",
    "count": 113,
    "uniques": 76
  },
  {
    "referrer": "ecosia.org",
    "count": 52,
    "uniques": 8
  },
  {
    "referrer": "pypi.org",
    "count": 19,
    "uniques": 15
  },
  {
    "referrer": "selene-docs-test.readthedocs.io",
    "count": 8,
    "uniques": 3
  },
  {
    "referrer": "qiita.com",
    "count": 6,
    "uniques": 5
  },
  {
    "referrer": "autotest.how",
    "count": 4,
    "uniques": 2
  },
  {
    "referrer": "Baidu",
    "count": 2,
    "uniques": 2
  },
  {
    "referrer": "qwiki.nixsolutions.com",
    "count": 2,
    "uniques": 2
  },
  {
    "referrer": "DuckDuckGo",
    "count": 2,
    "uniques": 1
  }
]