[
  {
    "path": "/yashaka/selene",
    "title": "yashaka/selene: User-oriented Web UI browser tests in Python",
    "count": 297,
    "uniques": 163
  },
  {
    "path": "/yashaka/selene/tree/master/examples",
    "title": "selene/examples at master · yashaka/selene · GitHub",
    "count": 60,
    "uniques": 20
  },
  {
    "path": "/yashaka/selene/blob/master/README.md",
    "title": "selene/README.md at master · yashaka/selene · GitHub",
    "count": 54,
    "uniques": 18
  },
  {
    "path": "/yashaka/selene/tree/master/selene",
    "title": "selene/selene at master · yashaka/selene · GitHub",
    "count": 43,
    "uniques": 14
  },
  {
    "path": "/yashaka/selene/tree/master/tests",
    "title": "selene/tests at master · yashaka/selene · GitHub",
    "count": 41,
    "uniques": 13
  },
  {
    "path": "/yashaka/selene/releases",
    "title": "Releases · yashaka/selene · GitHub",
    "count": 40,
    "uniques": 14
  },
  {
    "path": "/yashaka/selene/issues",
    "title": "Issues · yashaka/selene · GitHub",
    "count": 29,
    "uniques": 8
  },
  {
    "path": "/yashaka/selene/blob/master/examples/run_cross_platform/tests/acceptance_test.py",
    "title": "selene/examples/run_cross_platform/tests/acceptance_test.py at master · yasha...",
    "count": 28,
    "uniques": 9
  },
  {
    "path": "/yashaka/selene/pulls",
    "title": "Pull requests · yashaka/selene · GitHub",
    "count": 21,
    "uniques": 6
  },
  {
    "path": "/yashaka/selene/tree/master/tests/examples",
    "title": "selene/tests/examples at master · yashaka/selene · GitHub",
    "count": 19,
    "uniques": 5
  }
]