[
  {
    "referrer": "Google",
    "count": 452,
    "uniques": 141
  },
  {
    "referrer": "github.com",
    "count": 192,
    "uniques": 40
  },
  {
    "referrer": "automated-testing.info",
    "count": 18,
    "uniques": 9
  },
  {
    "referrer": "DuckDuckGo",
    "count": 10,
    "uniques": 5
  },
  {
    "referrer": "selene-docs-test.readthedocs.io",
    "count": 10,
    "uniques": 3
  },
  {
    "referrer": "yandex.ru",
    "count": 7,
    "uniques": 6
  },
  {
    "referrer": "pypi.org",
    "count": 7,
    "uniques": 5
  },
  {
    "referrer": "youtube.com",
    "count": 7,
    "uniques": 3
  },
  {
    "referrer": "Bing",
    "count": 5,
    "uniques": 4
  },
  {
    "referrer": "qiita.com",
    "count": 4,
    "uniques": 2
  }
]