[
  {
    "path": "/yashaka/selene",
    "title": "yashaka/selene: User-oriented Web UI browser tests in Python",
    "count": 397,
    "uniques": 172
  },
  {
    "path": "/yashaka/selene/pulls",
    "title": "Pull requests · yashaka/selene · GitHub",
    "count": 92,
    "uniques": 15
  },
  {
    "path": "/yashaka/selene/releases",
    "title": "Releases · yashaka/selene · GitHub",
    "count": 72,
    "uniques": 9
  },
  {
    "path": "/yashaka/selene/issues",
    "title": "Issues · yashaka/selene · GitHub",
    "count": 61,
    "uniques": 14
  },
  {
    "path": "/yashaka/selene/issues/128",
    "title": "alert = driver().switch_to.alert alert.accept() throws NoAlertPresentExceptio...",
    "count": 33,
    "uniques": 29
  },
  {
    "path": "/yashaka/selene/search",
    "title": "Search · _start_driver",
    "count": 31,
    "uniques": 5
  },
  {
    "path": "/yashaka/selene/actions",
    "title": "Actions · yashaka/selene",
    "count": 31,
    "uniques": 3
  },
  {
    "path": "/yashaka/selene/pull/343",
    "title": "upgrade codecov action 1.4.1 -> 1.5.0 by aleksandr-kotlyar · Pull Request #34...",
    "count": 26,
    "uniques": 2
  },
  {
    "path": "/yashaka/selene/tree/master/selene",
    "title": "selene/selene at master · yashaka/selene · GitHub",
    "count": 25,
    "uniques": 16
  },
  {
    "path": "/yashaka/selene/tree/master/tests",
    "title": "selene/tests at master · yashaka/selene · GitHub",
    "count": 23,
    "uniques": 11
  }
]