[
  {
    "path": "/yashaka/selene",
    "title": "yashaka/selene: User-oriented Web UI browser tests in Python",
    "count": 323,
    "uniques": 149
  },
  {
    "path": "/yashaka/selene/tree/master/selene",
    "title": "selene/selene at master · yashaka/selene · GitHub",
    "count": 49,
    "uniques": 11
  },
  {
    "path": "/yashaka/selene/tree/master/selene/support",
    "title": "selene/selene/support at master · yashaka/selene · GitHub",
    "count": 34,
    "uniques": 6
  },
  {
    "path": "/yashaka/selene/tree/master/selene/core",
    "title": "selene/selene/core at master · yashaka/selene · GitHub",
    "count": 33,
    "uniques": 5
  },
  {
    "path": "/yashaka/selene/issues/128",
    "title": "alert = driver().switch_to.alert alert.accept() throws NoAlertPresentExceptio...",
    "count": 26,
    "uniques": 20
  },
  {
    "path": "/yashaka/selene/blob/master/selene/core/entity.py",
    "title": "selene/entity.py at master · yashaka/selene · GitHub",
    "count": 25,
    "uniques": 2
  },
  {
    "path": "/yashaka/selene/tree/master/selene/support/shared",
    "title": "selene/selene/support/shared at master · yashaka/selene · GitHub",
    "count": 24,
    "uniques": 2
  },
  {
    "path": "/yashaka/selene/issues",
    "title": "Issues · yashaka/selene · GitHub",
    "count": 20,
    "uniques": 8
  },
  {
    "path": "/yashaka/selene/blob/master/selene/support/shared/browser.py",
    "title": "selene/browser.py at master · yashaka/selene · GitHub",
    "count": 19,
    "uniques": 1
  },
  {
    "path": "/yashaka/selene/tree/master/selene/support/conditions",
    "title": "selene/selene/support/conditions at master · yashaka/selene · GitHub",
    "count": 19,
    "uniques": 1
  }
]