{
  "count": 715,
  "uniques": 55,
  "clones": [
    {
      "timestamp": "2023-04-22T00:00:00Z",
      "count": 8,
      "uniques": 4
    },
    {
      "timestamp": "2023-04-23T00:00:00Z",
      "count": 11,
      "uniques": 5
    },
    {
      "timestamp": "2023-04-24T00:00:00Z",
      "count": 139,
      "uniques": 8
    },
    {
      "timestamp": "2023-04-25T00:00:00Z",
      "count": 101,
      "uniques": 10
    },
    {
      "timestamp": "2023-04-26T00:00:00Z",
      "count": 95,
      "uniques": 8
    },
    {
      "timestamp": "2023-04-27T00:00:00Z",
      "count": 163,
      "uniques": 10
    },
    {
      "timestamp": "2023-04-28T00:00:00Z",
      "count": 198,
      "uniques": 10
    }
  ]
}