{
  "count": 1181,
  "uniques": 71,
  "clones": [
    {
      "timestamp": "2023-09-14T00:00:00Z",
      "count": 215,
      "uniques": 11
    },
    {
      "timestamp": "2023-09-15T00:00:00Z",
      "count": 279,
      "uniques": 10
    },
    {
      "timestamp": "2023-09-16T00:00:00Z",
      "count": 112,
      "uniques": 7
    },
    {
      "timestamp": "2023-09-17T00:00:00Z",
      "count": 82,
      "uniques": 11
    },
    {
      "timestamp": "2023-09-18T00:00:00Z",
      "count": 200,
      "uniques": 9
    },
    {
      "timestamp": "2023-09-19T00:00:00Z",
      "count": 142,
      "uniques": 13
    },
    {
      "timestamp": "2023-09-20T00:00:00Z",
      "count": 151,
      "uniques": 10
    }
  ]
}