[
  {
    "path": "/yashaka/selene",
    "title": "yashaka/selene: User-oriented Web UI browser tests in Python",
    "count": 441,
    "uniques": 230
  },
  {
    "path": "/yashaka/selene/issues",
    "title": "Issues · yashaka/selene · GitHub",
    "count": 40,
    "uniques": 19
  },
  {
    "path": "/yashaka/selene/tree/master/tests",
    "title": "selene/tests at master · yashaka/selene · GitHub",
    "count": 35,
    "uniques": 15
  },
  {
    "path": "/yashaka/selene/tree/master/selene",
    "title": "selene/selene at master · yashaka/selene · GitHub",
    "count": 32,
    "uniques": 20
  },
  {
    "path": "/yashaka/selene/releases",
    "title": "Releases · yashaka/selene · GitHub",
    "count": 27,
    "uniques": 13
  },
  {
    "path": "/yashaka/selene/releases/tag/2.0.0b3",
    "title": "Release 2.0.0b3 · yashaka/selene · GitHub",
    "count": 26,
    "uniques": 16
  },
  {
    "path": "/yashaka/selene/actions",
    "title": "Actions · yashaka/selene · GitHub",
    "count": 23,
    "uniques": 4
  },
  {
    "path": "/yashaka/selene/commits/master",
    "title": "Commits · yashaka/selene · GitHub",
    "count": 22,
    "uniques": 18
  },
  {
    "path": "/yashaka/selene/pulls",
    "title": "Pull requests · yashaka/selene · GitHub",
    "count": 21,
    "uniques": 9
  },
  {
    "path": "/yashaka/selene/issues/287",
    "title": "from selenium to selene · Issue #287 · yashaka/selene · GitHub",
    "count": 18,
    "uniques": 12
  }
]